wagtail_news_image-0.0.2.dist-info/METADATA
wagtail_news_image-0.0.2.dist-info/RECORD
wagtail_news_image-0.0.2.dist-info/WHEEL
wagtail_news_image-0.0.2.dist-info/top_level.txt
wagtailnewsimage/__init__.py
wagtailnewsimage/monkey_patch.py
wagtailnewsimage/rich_text.py
wagtailnewsimage/serializers.py
wagtailnewsimage/urls.py
wagtailnewsimage/views.py
wagtailnewsimage/wagtail_hooks.py
wagtailnewsimage/static/wagtailnewsimage/js/wagtailnewsimage.js
