Metadata-Version: 2.1
Name: wagtail-news-image
Version: 0.0.2
Summary: An extended Draftail image block for news sites.
Home-page: https://github.com/StocksDigital/wagtail-news-image
Author: Matthew Segal
Author-email: matthew.segal@stocksdigital.com
License: MIT
Platform: UNKNOWN
Classifier: Development Status :: 4 - Beta
Classifier: Environment :: Web Environment
Classifier: Intended Audience :: Developers
Classifier: License :: OSI Approved :: MIT License
Classifier: Operating System :: OS Independent
Classifier: Programming Language :: Python
Classifier: Programming Language :: Python :: 3.5
Classifier: Programming Language :: Python :: 3.6
Classifier: Framework :: Django
Classifier: Framework :: Wagtail
Classifier: Framework :: Wagtail :: 2
Classifier: Topic :: Internet :: WWW/HTTP
Classifier: Topic :: Internet :: WWW/HTTP :: Dynamic Content
Provides-Extra: test
Requires-Dist: wagtail (>=2)
Requires-Dist: djangorestframework (>=3)
Provides-Extra: test
Requires-Dist: pytest (>=3.5); extra == 'test'
